speech_gateway/__init__.py
speech_gateway/cache/__init__.py
speech_gateway/cache/file.py
speech_gateway/converter/__init__.py
speech_gateway/converter/mp3.py
speech_gateway/converter/mulaw.py
speech_gateway/converter/pcm.py
speech_gateway/converter/wave.py
speech_gateway/gateway/__init__.py
speech_gateway/gateway/azure.py
speech_gateway/gateway/nijivoice.py
speech_gateway/gateway/nijivoice_encoded.py
speech_gateway/gateway/openai_speech.py
speech_gateway/gateway/sbv2.py
speech_gateway/gateway/unified.py
speech_gateway/gateway/voicevox.py
speech_gateway/performance_recorder/__init__.py
speech_gateway/performance_recorder/postgres.py
speech_gateway/performance_recorder/sqlite.py
speech_gateway/source/__init__.py
speech_gateway/source/azure.py
speech_gateway/source/nijivoice.py
speech_gateway/source/nijivoice_encoded.py
speech_gateway/source/openai_speech.py
speech_gateway/source/sbv2.py
speech_gateway/source/voicevox.py
speech_gateway-0.1.8.dist-info/LICENSE
speech_gateway-0.1.8.dist-info/METADATA
speech_gateway-0.1.8.dist-info/WHEEL
speech_gateway-0.1.8.dist-info/top_level.txt
speech_gateway-0.1.8.dist-info/RECORD
