Metadata-Version: 2.1
Name: speech-gateway
Version: 0.1.8
Summary: A reverse proxy server that enhances speech synthesis with essential, extensible features. 🦉💬
Home-page: https://github.com/uezo/speech-gateway
Author: uezo
Author-email: uezo@uezo.net
Maintainer: uezo
Maintainer-email: uezo@uezo.net
License: Apache v2
Classifier: Programming Language :: Python :: 3
License-File: LICENSE
Requires-Dist: aiofiles==24.1.0
Requires-Dist: fastapi==0.115.6
Requires-Dist: httpx==0.28.1
Requires-Dist: uvicorn==0.34.0
